ymago/__init__.py
ymago/_version.py
ymago/api.py
ymago/cli.py
ymago/config.py
ymago/constants.py
ymago/models.py
ymago/core/__init__.py
ymago/core/backends.py
ymago/core/batch_parser.py
ymago/core/cloud_storage.py
ymago/core/generation.py
ymago/core/io_utils.py
ymago/core/notifications.py
ymago/core/storage.py
ymago-0.1.2.dist-info/METADATA
ymago-0.1.2.dist-info/WHEEL
ymago-0.1.2.dist-info/entry_points.txt
ymago-0.1.2.dist-info/licenses/LICENSE
ymago-0.1.2.dist-info/RECORD
