Metadata-Version: 2.4
Name: ymago
Version: 0.1.2
Summary: An advanced, asynchronous command-line toolkit and Python library for generative AI media.
Project-URL: Homepage, https://github.com/aurichalcite/ymago
Project-URL: Documentation, https://github.com/aurichalcite/ymago#readme
Project-URL: Repository, https://github.com/aurichalcite/ymago.git
Project-URL: Issues, https://github.com/aurichalcite/ymago/issues
Author-email: Andrej Mäsiar <86407432+aurichalcite@users.noreply.github.com>
License: MIT License
License-File: LICENSE
Keywords: ai,cli,gemini,generative,image,video
Classifier: Development Status :: 4 - Beta
Classifier: Intended Audience :: Developers
Classifier: License :: OSI Approved :: MIT License
Classifier: Programming Language :: Python :: 3.10
Classifier: Programming Language :: Python :: 3.11
Classifier: Programming Language :: Python :: 3.12
Classifier: Programming Language :: Python :: 3.13
Classifier: Topic :: Multimedia :: Graphics
Classifier: Topic :: Software Development :: Libraries :: Python Modules
Classifier: Typing :: Typed
Requires-Python: >=3.10
Requires-Dist: aiocsv>=1.3.2
Requires-Dist: aiofiles>=24.1.0
Requires-Dist: aiohttp>=3.12.15
Requires-Dist: google-genai>=1.36.0
Requires-Dist: pydantic<3.0,>=2.0
Requires-Dist: rich>=14.1.0
Requires-Dist: tenacity>=9.0.0
Requires-Dist: tomli>=2.2.1
Requires-Dist: typer>=0.17.4
Provides-Extra: aws
Requires-Dist: aioboto3>=13.2.0; extra == 'aws'
Requires-Dist: botocore>=1.35.0; extra == 'aws'
Provides-Extra: cloud
Requires-Dist: aioboto3>=13.2.0; extra == 'cloud'
Requires-Dist: botocore>=1.35.0; extra == 'cloud'
Requires-Dist: gcloud-aio-storage>=9.3.0; extra == 'cloud'
Provides-Extra: dev
Requires-Dist: aioboto3>=13.2.0; extra == 'dev'
Requires-Dist: aioresponses>=0.7.6; extra == 'dev'
Requires-Dist: aresponses>=3.0.0; extra == 'dev'
Requires-Dist: bandit>=1.8.6; extra == 'dev'
Requires-Dist: gcloud-aio-storage>=9.3.0; extra == 'dev'
Requires-Dist: mypy-boto3-s3>=1.28.0; extra == 'dev'
Requires-Dist: mypy>=1.17.1; extra == 'dev'
Requires-Dist: pydantic<3.0,>=2.0; extra == 'dev'
Requires-Dist: ruff>=0.13.0; extra == 'dev'
Requires-Dist: tomli>=2.2.1; extra == 'dev'
Requires-Dist: types-aiofiles>=24.1.0.20250822; extra == 'dev'
Provides-Extra: docs
Requires-Dist: myst-parser>=3.0.0; extra == 'docs'
Requires-Dist: sphinx-autodoc-typehints>=2.5.0; extra == 'docs'
Requires-Dist: sphinx-rtd-theme>=3.0.0; extra == 'docs'
Requires-Dist: sphinx>=8.0.0; extra == 'docs'
Requires-Dist: sphinxcontrib-mermaid>=1.0.0; extra == 'docs'
Provides-Extra: gcp
Requires-Dist: gcloud-aio-storage>=9.3.0; extra == 'gcp'
Provides-Extra: r2
Requires-Dist: aioboto3>=13.2.0; extra == 'r2'
Requires-Dist: botocore>=1.35.0; extra == 'r2'
Provides-Extra: test
Requires-Dist: hypothesis>=6.100.0; extra == 'test'
Requires-Dist: pytest-asyncio>=1.1.0; extra == 'test'
Requires-Dist: pytest-benchmark>=5.0.0; extra == 'test'
Requires-Dist: pytest-cov>=7.0.0; extra == 'test'
Requires-Dist: pytest-mock>=3.14.0; extra == 'test'
Requires-Dist: pytest-xdist>=3.8.0; extra == 'test'
Requires-Dist: pytest>=8.4.2; extra == 'test'
